gridtools_cpp/__init__.py
gridtools_cpp/py.typed
gridtools_cpp/data/include/gridtools/layout_transformation.hpp
gridtools_cpp/data/include/gridtools/meta.hpp
gridtools_cpp/data/include/gridtools/reduction.hpp
gridtools_cpp/data/include/gridtools/boundaries/apply.hpp
gridtools_cpp/data/include/gridtools/boundaries/apply_gpu.hpp
gridtools_cpp/data/include/gridtools/boundaries/bound_bc.hpp
gridtools_cpp/data/include/gridtools/boundaries/boundary.hpp
gridtools_cpp/data/include/gridtools/boundaries/comm_traits.hpp
gridtools_cpp/data/include/gridtools/boundaries/copy.hpp
gridtools_cpp/data/include/gridtools/boundaries/direction.hpp
gridtools_cpp/data/include/gridtools/boundaries/distributed_boundaries.hpp
gridtools_cpp/data/include/gridtools/boundaries/grid_predicate.hpp
gridtools_cpp/data/include/gridtools/boundaries/predicate.hpp
gridtools_cpp/data/include/gridtools/boundaries/value.hpp
gridtools_cpp/data/include/gridtools/boundaries/zero.hpp
gridtools_cpp/data/include/gridtools/common/array.hpp
gridtools_cpp/data/include/gridtools/common/array_addons.hpp
gridtools_cpp/data/include/gridtools/common/atomic_cuda.hpp
gridtools_cpp/data/include/gridtools/common/atomic_functions.hpp
gridtools_cpp/data/include/gridtools/common/atomic_host.hpp
gridtools_cpp/data/include/gridtools/common/compose.hpp
gridtools_cpp/data/include/gridtools/common/const_ptr_deref.hpp
gridtools_cpp/data/include/gridtools/common/ct_dispatch.hpp
gridtools_cpp/data/include/gridtools/common/cuda_is_ptr.hpp
gridtools_cpp/data/include/gridtools/common/cuda_runtime.hpp
gridtools_cpp/data/include/gridtools/common/cuda_type_traits.hpp
gridtools_cpp/data/include/gridtools/common/cuda_util.hpp
gridtools_cpp/data/include/gridtools/common/defs.hpp
gridtools_cpp/data/include/gridtools/common/for_each.hpp
gridtools_cpp/data/include/gridtools/common/functional.hpp
gridtools_cpp/data/include/gridtools/common/gt_math.hpp
gridtools_cpp/data/include/gridtools/common/halo_descriptor.hpp
gridtools_cpp-2.3.9.dist-info/METADATA
gridtools_cpp-2.3.9.dist-info/WHEEL
gridtools_cpp-2.3.9.dist-info/top_level.txt
gridtools_cpp-2.3.9.dist-info/RECORD
