Metadata-Version: 2.4
Name: gridtools-cpp
Version: 2.3.9
Home-page: https://gridtools.github.io
Author: ETH Zurich
Author-email: gridtools@cscs.ch
Project-URL: Source Code, https://github.com/GridTools/gridtools
Platform: any
Classifier: Development Status :: 5 - Production/Stable
Classifier: Intended Audience :: Science/Research
Classifier: License :: OSI Approved :: BSD License
Classifier: Operating System :: OS Independent
Classifier: Programming Language :: Python :: 3 :: Only
Classifier: Topic :: Scientific/Engineering :: Atmospheric Science
Classifier: Topic :: Scientific/Engineering :: Mathematics
Classifier: Topic :: Scientific/Engineering :: Physics
Requires-Python: >=3.8
